lottie_inline_tool/__init__.py
lottie_inline_tool/main.py
lottie_inline_tool-0.1.0.dist-info/METADATA
lottie_inline_tool-0.1.0.dist-info/WHEEL
lottie_inline_tool-0.1.0.dist-info/entry_points.txt
lottie_inline_tool-0.1.0.dist-info/top_level.txt
lottie_inline_tool-0.1.0.dist-info/RECORD
